sh_batch_grid_builder/__init__.py
sh_batch_grid_builder/cli.py
sh_batch_grid_builder/crs.py
sh_batch_grid_builder/geo.py
sh_batch_grid_builder-0.2.2.dist-info/METADATA
sh_batch_grid_builder-0.2.2.dist-info/WHEEL
sh_batch_grid_builder-0.2.2.dist-info/entry_points.txt
sh_batch_grid_builder-0.2.2.dist-info/top_level.txt
sh_batch_grid_builder-0.2.2.dist-info/RECORD
