Metadata-Version: 2.4
Name: sh-batch-grid-builder
Version: 0.2.2
Summary: A tool for generating projection grid aligned bounding boxes and pixelated geometries from AOI (Area of Interest) files for Sentinel Hub Batch V2 API on CDSE
Author-email: Maxim Lamare <maxim.lamare@sinergise.com>
License: MIT
Keywords: gis,geospatial,grid,pixelation,bounding-box
Classifier: Development Status :: 4 - Beta
Classifier: Intended Audience :: Developers
Classifier: Intended Audience :: Science/Research
Classifier: License :: OSI Approved :: MIT License
Classifier: Programming Language :: Python :: 3
Classifier: Programming Language :: Python :: 3.8
Classifier: Programming Language :: Python :: 3.9
Classifier: Programming Language :: Python :: 3.10
Classifier: Programming Language :: Python :: 3.11
Classifier: Topic :: Scientific/Engineering :: GIS
Requires-Python: >=3.8
Requires-Dist: geopandas>=0.12.0
Requires-Dist: pyproj>=3.4.0
Requires-Dist: shapely>=2.0.0
Requires-Dist: rasterio>=1.3.0
Requires-Dist: numpy>=1.21.0
Provides-Extra: dev
Requires-Dist: pytest>=7.0.0; extra == "dev"
Requires-Dist: pytest-cov>=4.0.0; extra == "dev"
